chkpt.py
chkpt-0.1.0.dist-info/LICENSE
chkpt-0.1.0.dist-info/METADATA
chkpt-0.1.0.dist-info/WHEEL
chkpt-0.1.0.dist-info/top_level.txt
chkpt-0.1.0.dist-info/RECORD
