Metadata-Version: 2.1
Name: chkpt
Version: 0.1.0
Summary: A tiny pipeline builder
Home-page: https://github.com/msuozzo/chkpt
Author: Matthew Suozzo
License: UNKNOWN
Project-URL: Bug Reports, https://github.com/msuozzo/chkpt/issues
Project-URL: Source, https://github.com/msuozzo/chkpt/
Keywords: pipeline,data,prototyping
Platform: UNKNOWN
Classifier: Development Status :: 3 - Alpha
Classifier: Intended Audience :: Developers
Classifier: Topic :: Software Development :: Build Tools
Classifier: License :: OSI Approved :: MIT License
Classifier: Programming Language :: Python :: 3
Classifier: Programming Language :: Python :: 3.6
Classifier: Programming Language :: Python :: 3.7
Classifier: Programming Language :: Python :: 3.8
Classifier: Programming Language :: Python :: 3.9
Classifier: Programming Language :: Python :: 3.10
Classifier: Programming Language :: Python :: 3 :: Only
Requires-Python: >=3.6, <4
License-File: LICENSE
